bluebook/__init__.py
bluebook/configuration.py
bluebook/data_models.py
bluebook/database_manager.py
bluebook/fl.py
bluebook/generator.py
bluebook/static/images/book.png
bluebook/static/images/book.svg
bluebook/static/styles.css
bluebook/templates/base.html.j2
bluebook/templates/check.html.j2
bluebook/templates/exam_constructor.html.j2
bluebook/templates/root.html.j2
bluebook/templates/saved_questions.html.j2
bluebook/templates/stripped_base.html.j2
bluebook/templates/token_prompt.html.j2
bluebook/token_manager.py
student_bluebook-1.1.3.dist-info/METADATA
student_bluebook-1.1.3.dist-info/WHEEL
student_bluebook-1.1.3.dist-info/entry_points.txt
student_bluebook-1.1.3.dist-info/licenses/LICENSE
student_bluebook-1.1.3.dist-info/RECORD
