Metadata-Version: 2.4
Name: student-bluebook
Version: 1.1.3
Summary: Blue Book generates multiple-choice questions for IT certifications, e.g. CompTIA A+ and Security+
License-File: LICENSE
Author: Ilya Smut
Author-email: ilya.smut.off.g@gmail.com
Requires-Python: >=3.10
Classifier: Programming Language :: Python :: 3
Classifier: Programming Language :: Python :: 3.10
Classifier: Programming Language :: Python :: 3.11
Classifier: Programming Language :: Python :: 3.12
Classifier: Programming Language :: Python :: 3.13
Classifier: Programming Language :: Python :: 3.14
Requires-Dist: bleach (>=6.2.0,<7.0.0)
Requires-Dist: click (>=8.1.8,<9.0.0)
Requires-Dist: flask (==3.1.1)
Requires-Dist: google-genai (>=1.2.0,<2.0.0)
Requires-Dist: jinja2 (==3.1.6)
Requires-Dist: mypy (>=1.16.0,<2.0.0)
Requires-Dist: pydantic (>=2.10.6,<3.0.0)
Requires-Dist: ruff (>=0.11.12,<0.12.0)
Requires-Dist: sqlmodel (>=0.0.24,<0.0.25)
Requires-Dist: types-bleach (>=6.2.0.20250514,<7.0.0.0)
Project-URL: Documentation, https://github.com/ilya-smut/blue-book/wiki
Project-URL: Homepage, https://student-bluebook.notion.site/
Project-URL: Repository, https://github.com/ilya-smut/blue-book
